pysqlx_core-0.2.3.dist-info/METADATA
pysqlx_core-0.2.3.dist-info/WHEEL
pysqlx_core-0.2.3.dist-info/licenses/LICENSE
pysqlx_core/__init__.py
pysqlx_core/__init__.pyi
pysqlx_core/py.typed
pysqlx_core/pysqlx_core.cp311-win32.pyd
pysqlx_core-0.2.3.dist-info/RECORD
