Metadata-Version: 2.3
Name: pysqlx-core
Version: 0.2.3
Classifier: Development Status :: 3 - Alpha
Classifier: Programming Language :: Rust
Classifier: Programming Language :: Python :: Implementation :: CPython
Classifier: Programming Language :: Python :: Implementation :: PyPy
Classifier: Programming Language :: Python
Classifier: Programming Language :: Python :: 3
Classifier: Programming Language :: Python :: 3 :: Only
Classifier: Programming Language :: Python :: 3.8
Classifier: Programming Language :: Python :: 3.9
Classifier: Programming Language :: Python :: 3.10
Classifier: Programming Language :: Python :: 3.11
Classifier: Programming Language :: Python :: 3.12
Classifier: Programming Language :: Python :: 3.13
Classifier: Programming Language :: Rust
Classifier: Intended Audience :: Developers
Classifier: Intended Audience :: Information Technology
Classifier: Intended Audience :: System Administrators
Classifier: Intended Audience :: Other Audience
Classifier: License :: OSI Approved :: MIT License
Classifier: Operating System :: POSIX :: Linux
Classifier: Operating System :: Microsoft :: Windows
Classifier: Operating System :: MacOS
Classifier: Topic :: Database
Classifier: Topic :: Internet
Classifier: Topic :: Software Development :: Libraries :: Application Frameworks
Classifier: Topic :: Software Development :: Libraries :: Python Modules
Classifier: Topic :: Software Development :: Libraries
Classifier: Topic :: Software Development
Classifier: Typing :: Typed
Classifier: Framework :: AsyncIO
Classifier: Framework :: AnyIO
Classifier: Framework :: FastAPI
Classifier: Framework :: Flask
Classifier: Framework :: IPython
License-File: LICENSE
Summary: A fast and async SQL database wrapper for Python, with support for MySQL, PostgreSQL, SQLite and MS SQL Server.
Keywords: async,database,sql,faster,pysqlx
Author-email: Carlos Rian <crian.rian@gmail.com>
Requires-Python: >=3.8
Project-URL: Homepage, https://github.com/carlos-rian/pysqlx-core
Project-URL: Source, https://github.com/carlos-rian/pysqlx-core
